[
  {
    "id": 1,
    "name": "Katrina",
    "position": "Elementarey Teacher",
    "exp": [
      "B.A in Drama, Studio Practice as well as Art History & Visual Culture, Rhodes University",
      "Head Teacher, Apax Leaders"
    ],
    "img": "/images/sub/point-avenue/all-elementary-courses/mentor_01.png"
  },
  {
    "id": 2,
    "name": "Jesika",
    "position": "Elementarey Teacher",
    "exp": [
      "B.A in Drama, Studio Practice as well as Art History & Visual Culture, Rhodes University",
      "Head Teacher, Apax Leaders"
    ],
    "img":  "/images/sub/point-avenue/all-elementary-courses/mentor_02.png"
  },
  {
    "id": 3,
    "name": "Amanda",
    "position": "Elementarey Teacher",
    "exp": [
      "B.A in Drama, Studio Practice as well as Art History & Visual Culture, Rhodes University",
      "Head Teacher, Apax Leaders"
    ],
    "img":  "/images/sub/point-avenue/all-elementary-courses/mentor_03.png"
  }
]